<?xml version="1.0" encoding="utf-8"?>
<clothing-items>
 <clothing>
  <id>
   378255733
  </id>
  <name>
   Ellesse Jeans B-9712
  </name>
  <category>
   Jeans
  </category>
  <size>
   XL
  </size>
  <color>
   Зеленый
  </color>
  <material>
   Нейлон
  </material>
  <price>
   500496
  </price>
  <rating>
   4.34
  </rating>
  <reviews>
   992242
  </reviews>
  <new>
   -
  </new>
  <exclusive>
   yes
  </exclusive>
  <sporty>
   yes
  </sporty>
 </clothing>
 <clothing>
  <id>
   323326118
  </id>
  <name>
   Ellesse Pants M-7082
  </name>
  <category>
   Pants
  </category>
  <size>
   M
  </size>
  <color>
   Голубой
  </color>
  <material>
   Хлопок
  </material>
  <price>
   154979
  </price>
  <rating>
   2.74
  </rating>
  <reviews>
   920743
  </reviews>
  <new>
   -
  </new>
  <exclusive>
   yes
  </exclusive>
  <sporty>
   no
  </sporty>
 </clothing>
 <clothing>
  <id>
   149715745
  </id>
  <name>
   Vans Pants J-8562
  </name>
  <category>
   Pants
  </category>
  <size>
   XL
  </size>
  <color>
   Фиолетовый
  </color>
  <material>
   Вискоза
  </material>
  <price>
   445797
  </price>
  <rating>
   2.32
  </rating>
  <reviews>
   253202
  </reviews>
  <new>
   -
  </new>
 </clothing>
 <clothing>
  <id>
   535573145
  </id>
  <name>
   Reebok Pants F-5341
  </name>
  <category>
   Pants
  </category>
  <size>
   S
  </size>
  <color>
   Синий
  </color>
  <material>
   Полиэстер
  </material>
  <price>
   210274
  </price>
  <rating>
   4.2
  </rating>
  <reviews>
   358431
  </reviews>
  <new>
   -
  </new>
  <sporty>
   no
  </sporty>
 </clothing>
 <clothing>
  <id>
   517940896
  </id>
  <name>
   PleinSport Gloves S-6625
  </name>
  <category>
   Gloves
  </category>
  <size>
   L
  </size>
  <color>
   Желтый
  </color>
  <material>
   Вискоза
  </material>
  <price>
   927274
  </price>
  <rating>
   2.81
  </rating>
  <reviews>
   406246
  </reviews>
  <new>
   -
  </new>
  <exclusive>
   yes
  </exclusive>
  <sporty>
   no
  </sporty>
 </clothing>
 <clothing>
  <id>
   718146629
  </id>
  <name>
   Vans Dress Z-1328
  </name>
  <category>
   Dress
  </category>
  <size>
   XL
  </size>
  <color>
   Голубой
  </color>
  <material>
   Шерсть
  </material>
  <price>
   153253
  </price>
  <rating>
   2.56
  </rating>
  <reviews>
   236013
  </reviews>
  <new>
   -
  </new>
  <sporty>
   yes
  </sporty>
 </clothing>
 <clothing>
  <id>
   841481655
  </id>
  <name>
   Ellesse Gloves B-3024
  </name>
  <category>
   Gloves
  </category>
  <size>
   L
  </size>
  <color>
   Зеленый
  </color>
  <material>
   Кожа
  </material>
  <price>
   247890
  </price>
  <rating>
   2.27
  </rating>
  <reviews>
   113238
  </reviews>
  <new>
   +
  </new>
  <exclusive>
   no
  </exclusive>
 </clothing>
 <clothing>
  <id>
   878439197
  </id>
  <name>
   Brooks Socks L-9438
  </name>
  <category>
   Socks
  </category>
  <size>
   XL
  </size>
  <color>
   Оранжевый
  </color>
  <material>
   Полиэстер
  </material>
  <price>
   428781
  </price>
  <rating>
   3.01
  </rating>
  <reviews>
   873036
  </reviews>
  <new>
   -
  </new>
  <sporty>
   yes
  </sporty>
 </clothing>
 <clothing>
  <id>
   892991833
  </id>
  <name>
   DC Hat D-4000
  </name>
  <category>
   Hat
  </category>
  <size>
   M
  </size>
  <color>
   Фиолетовый
  </color>
  <material>
   Нейлон
  </material>
  <price>
   963723
  </price>
  <rating>
   2.66
  </rating>
  <reviews>
   161573
  </reviews>
  <exclusive>
   yes
  </exclusive>
 </clothing>
 <clothing>
  <id>
   275327769
  </id>
  <name>
   PleinSport Shirt F-8534
  </name>
  <category>
   Shirt
  </category>
  <size>
   M
  </size>
  <color>
   Желтый
  </color>
  <material>
   Полиэстер
  </material>
  <price>
   743941
  </price>
  <rating>
   2.73
  </rating>
  <reviews>
   476476
  </reviews>
  <exclusive>
   yes
  </exclusive>
 </clothing>
 <clothing>
  <id>
   679558666
  </id>
  <name>
   Under Armour Belts J-1513
  </name>
  <category>
   Belts
  </category>
  <size>
   XL
  </size>
  <color>
   Фиолетовый
  </color>
  <material>
   Кожа
  </material>
  <price>
   967635
  </price>
  <rating>
   3.02
  </rating>
  <reviews>
   914869
  </reviews>
  <new>
   +
  </new>
 </clothing>
 <clothing>
  <id>
   359012697
  </id>
  <name>
   Ellesse Shirt U-1786
  </name>
  <category>
   Shirt
  </category>
  <size>
   M
  </size>
  <color>
   Фиолетовый
  </color>
  <material>
   Нейлон
  </material>
  <price>
   376979
  </price>
  <rating>
   4.01
  </rating>
  <reviews>
   737550
  </reviews>
  <sporty>
   no
  </sporty>
 </clothing>
 <clothing>
  <id>
   832699045
  </id>
  <name>
   Adidas Sweater S-1827
  </name>
  <category>
   Sweater
  </category>
  <size>
   M
  </size>
  <color>
   Зеленый
  </color>
  <material>
   Шерсть
  </material>
  <price>
   596688
  </price>
  <rating>
   4.97
  </rating>
  <reviews>
   49424
  </reviews>
  <sporty>
   no
  </sporty>
 </clothing>
 <clothing>
  <id>
   799905374
  </id>
  <name>
   Brooks Dress A-1109
  </name>
  <category>
   Dress
  </category>
  <size>
   XL
  </size>
  <color>
   Оранжевый
  </color>
  <material>
   Шелк
  </material>
  <price>
   480761
  </price>
  <rating>
   4.91
  </rating>
  <reviews>
   63222
  </reviews>
  <new>
   +
  </new>
  <exclusive>
   yes
  </exclusive>
  <sporty>
   yes
  </sporty>
 </clothing>
 <clothing>
  <id>
   471650874
  </id>
  <name>
   Addidas Sweater I-9446
  </name>
  <category>
   Sweater
  </category>
  <size>
   L
  </size>
  <color>
   Оранжевый
  </color>
  <material>
   Шерсть
  </material>
  <price>
   862373
  </price>
  <rating>
   1.46
  </rating>
  <reviews>
   550561
  </reviews>
  <new>
   +
  </new>
 </clothing>
 <clothing>
  <id>
   137908250
  </id>
  <name>
   Vans T-shirt V-9478
  </name>
  <category>
   T-shirt
  </category>
  <size>
   L
  </size>
  <color>
   Оранжевый
  </color>
  <material>
   Полиэстер
  </material>
  <price>
   614248
  </price>
  <rating>
   1.4
  </rating>
  <reviews>
   409058
  </reviews>
  <sporty>
   yes
  </sporty>
 </clothing>
 <clothing>
  <id>
   283047456
  </id>
  <name>
   Brooks Jacket H-8630
  </name>
  <category>
   Jacket
  </category>
  <size>
   XL
  </size>
  <color>
   Синий
  </color>
  <material>
   Шелк
  </material>
  <price>
   372417
  </price>
  <rating>
   2.89
  </rating>
  <reviews>
   975910
  </reviews>
  <new>
   -
  </new>
  <exclusive>
   yes
  </exclusive>
  <sporty>
   no
  </sporty>
 </clothing>
 <clothing>
  <id>
   687657145
  </id>
  <name>
   Adidas Umbrellas O-8871
  </name>
  <category>
   Umbrellas
  </category>
  <size>
   L
  </size>
  <color>
   Желтый
  </color>
  <material>
   Полиэстер
  </material>
  <price>
   279090
  </price>
  <rating>
   1.26
  </rating>
  <reviews>
   726459
  </reviews>
  <exclusive>
   no
  </exclusive>
 </clothing>
 <clothing>
  <id>
   941931002
  </id>
  <name>
   Puma Dress F-7775
  </name>
  <category>
   Dress
  </category>
  <size>
   S
  </size>
  <color>
   Голубой
  </color>
  <material>
   Нейлон
  </material>
  <price>
   913177
  </price>
  <rating>
   2.78
  </rating>
  <reviews>
   296726
  </reviews>
  <new>
   +
  </new>
  <exclusive>
   yes
  </exclusive>
 </clothing>
 <clothing>
  <id>
   166276698
  </id>
  <name>
   Reebok Jeans A-9299
  </name>
  <category>
   Jeans
  </category>
  <size>
   L
  </size>
  <color>
   Голубой
  </color>
  <material>
   Полиэстер
  </material>
  <price>
   123047
  </price>
  <rating>
   1.09
  </rating>
  <reviews>
   691322
  </reviews>
  <new>
   -
  </new>
  <exclusive>
   no
  </exclusive>
 </clothing>
 <clothing>
  <id>
   262647286
  </id>
  <name>
   Lacoste Hat H-6760
  </name>
  <category>
   Hat
  </category>
  <size>
   XL
  </size>
  <color>
   Фиолетовый
  </color>
  <material>
   Вискоза
  </material>
  <price>
   934334
  </price>
  <rating>
   3.52
  </rating>
  <reviews>
   245020
  </reviews>
  <new>
   -
  </new>
  <exclusive>
   yes
  </exclusive>
 </clothing>
 <clothing>
  <id>
   796344834
  </id>
  <name>
   Reebok T-shirt U-5661
  </name>
  <category>
   T-shirt
  </category>
  <size>
   XXL
  </size>
  <color>
   Красный
  </color>
  <material>
   Полиэстер
  </material>
  <price>
   409892
  </price>
  <rating>
   4.3
  </rating>
  <reviews>
   349031
  </reviews>
  <new>
   +
  </new>
  <exclusive>
   no
  </exclusive>
  <sporty>
   no
  </sporty>
 </clothing>
 <clothing>
  <id>
   366346611
  </id>
  <name>
   Brooks Jeans U-2710
  </name>
  <category>
   Jeans
  </category>
  <size>
   XL
  </size>
  <color>
   Красный
  </color>
  <material>
   Полиэстер
  </material>
  <price>
   593251
  </price>
  <rating>
   4.31
  </rating>
  <reviews>
   141121
  </reviews>
  <sporty>
   no
  </sporty>
 </clothing>
 <clothing>
  <id>
   586715647
  </id>
  <name>
   DC Belts D-9492
  </name>
  <category>
   Belts
  </category>
  <size>
   S
  </size>
  <color>
   Красный
  </color>
  <material>
   Полиэстер
  </material>
  <price>
   481330
  </price>
  <rating>
   3.13
  </rating>
  <reviews>
   753627
  </reviews>
  <new>
   -
  </new>
  <exclusive>
   no
  </exclusive>
 </clothing>
 <clothing>
  <id>
   583341548
  </id>
  <name>
   Vans Hat T-5130
  </name>
  <category>
   Hat
  </category>
  <size>
   L
  </size>
  <color>
   Красный
  </color>
  <material>
   Вискоза
  </material>
  <price>
   697619
  </price>
  <rating>
   3.5
  </rating>
  <reviews>
   877280
  </reviews>
  <new>
   -
  </new>
  <exclusive>
   yes
  </exclusive>
  <sporty>
   yes
  </sporty>
 </clothing>
 <clothing>
  <id>
   354668254
  </id>
  <name>
   Asics Handbags B-1594
  </name>
  <category>
   Handbags
  </category>
  <size>
   L
  </size>
  <color>
   Желтый
  </color>
  <material>
   Лен
  </material>
  <price>
   843464
  </price>
  <rating>
   3.59
  </rating>
  <reviews>
   917391
  </reviews>
  <new>
   -
  </new>
  <sporty>
   no
  </sporty>
 </clothing>
 <clothing>
  <id>
   658511508
  </id>
  <name>
   Under Armour Blouse L-2467
  </name>
  <category>
   Blouse
  </category>
  <size>
   M
  </size>
  <color>
   Красный
  </color>
  <material>
   Лен
  </material>
  <price>
   697467
  </price>
  <rating>
   4.61
  </rating>
  <reviews>
   284577
  </reviews>
 </clothing>
 <clothing>
  <id>
   935715076
  </id>
  <name>
   Lacoste Shirt O-1076
  </name>
  <category>
   Shirt
  </category>
  <size>
   XXL
  </size>
  <color>
   Фиолетовый
  </color>
  <material>
   Нейлон
  </material>
  <price>
   654898
  </price>
  <rating>
   4.49
  </rating>
  <reviews>
   247477
  </reviews>
  <exclusive>
   no
  </exclusive>
 </clothing>
 <clothing>
  <id>
   741686508
  </id>
  <name>
   Nike Skirt R-9494
  </name>
  <category>
   Skirt
  </category>
  <size>
   XL
  </size>
  <color>
   Красный
  </color>
  <material>
   Нейлон
  </material>
  <price>
   995249
  </price>
  <rating>
   1.99
  </rating>
  <reviews>
   641011
  </reviews>
  <sporty>
   yes
  </sporty>
 </clothing>
</clothing-items>
