<?xml version="1.0" encoding="utf-8"?>
<clothing-items>
 <clothing>
  <id>
   408684414
  </id>
  <name>
   Lacoste Blouse F-6422
  </name>
  <category>
   Blouse
  </category>
  <size>
   L
  </size>
  <color>
   Синий
  </color>
  <material>
   Полиэстер
  </material>
  <price>
   279531
  </price>
  <rating>
   3.6
  </rating>
  <reviews>
   10885
  </reviews>
  <new>
   +
  </new>
 </clothing>
 <clothing>
  <id>
   989648417
  </id>
  <name>
   Brooks Jeans T-7602
  </name>
  <category>
   Jeans
  </category>
  <size>
   L
  </size>
  <color>
   Желтый
  </color>
  <material>
   Хлопок
  </material>
  <price>
   309632
  </price>
  <rating>
   4.6
  </rating>
  <reviews>
   822927
  </reviews>
  <new>
   -
  </new>
  <sporty>
   yes
  </sporty>
 </clothing>
 <clothing>
  <id>
   805900292
  </id>
  <name>
   New Balance Dress S-3237
  </name>
  <category>
   Dress
  </category>
  <size>
   XXL
  </size>
  <color>
   Голубой
  </color>
  <material>
   Кожа
  </material>
  <price>
   491200
  </price>
  <rating>
   2.91
  </rating>
  <reviews>
   696977
  </reviews>
  <new>
   -
  </new>
  <exclusive>
   yes
  </exclusive>
  <sporty>
   no
  </sporty>
 </clothing>
 <clothing>
  <id>
   624057779
  </id>
  <name>
   Ellesse T-shirt K-3884
  </name>
  <category>
   T-shirt
  </category>
  <size>
   S
  </size>
  <color>
   Зеленый
  </color>
  <material>
   Лен
  </material>
  <price>
   323478
  </price>
  <rating>
   3.76
  </rating>
  <reviews>
   646732
  </reviews>
  <new>
   +
  </new>
  <exclusive>
   no
  </exclusive>
  <sporty>
   yes
  </sporty>
 </clothing>
 <clothing>
  <id>
   261379784
  </id>
  <name>
   Lacoste Socks Q-6200
  </name>
  <category>
   Socks
  </category>
  <size>
   M
  </size>
  <color>
   Голубой
  </color>
  <material>
   Шерсть
  </material>
  <price>
   553465
  </price>
  <rating>
   3.72
  </rating>
  <reviews>
   476939
  </reviews>
  <new>
   +
  </new>
  <exclusive>
   no
  </exclusive>
 </clothing>
 <clothing>
  <id>
   591656811
  </id>
  <name>
   Adidas Skirt S-4168
  </name>
  <category>
   Skirt
  </category>
  <size>
   L
  </size>
  <color>
   Оранжевый
  </color>
  <material>
   Вискоза
  </material>
  <price>
   380516
  </price>
  <rating>
   2.38
  </rating>
  <reviews>
   80926
  </reviews>
  <sporty>
   yes
  </sporty>
 </clothing>
 <clothing>
  <id>
   559143429
  </id>
  <name>
   New Balance Shirt O-5933
  </name>
  <category>
   Shirt
  </category>
  <size>
   S
  </size>
  <color>
   Синий
  </color>
  <material>
   Полиэстер
  </material>
  <price>
   689587
  </price>
  <rating>
   2.87
  </rating>
  <reviews>
   597119
  </reviews>
  <exclusive>
   yes
  </exclusive>
 </clothing>
 <clothing>
  <id>
   349912237
  </id>
  <name>
   Lacoste Dress V-9689
  </name>
  <category>
   Dress
  </category>
  <size>
   S
  </size>
  <color>
   Зеленый
  </color>
  <material>
   Лен
  </material>
  <price>
   841051
  </price>
  <rating>
   1.91
  </rating>
  <reviews>
   481149
  </reviews>
  <exclusive>
   no
  </exclusive>
  <sporty>
   no
  </sporty>
 </clothing>
 <clothing>
  <id>
   946762458
  </id>
  <name>
   Nike Dress P-1257
  </name>
  <category>
   Dress
  </category>
  <size>
   S
  </size>
  <color>
   Красный
  </color>
  <material>
   Нейлон
  </material>
  <price>
   330001
  </price>
  <rating>
   4.31
  </rating>
  <reviews>
   253949
  </reviews>
  <exclusive>
   yes
  </exclusive>
  <sporty>
   yes
  </sporty>
 </clothing>
 <clothing>
  <id>
   541055598
  </id>
  <name>
   DC Blouse Q-1870
  </name>
  <category>
   Blouse
  </category>
  <size>
   S
  </size>
  <color>
   Синий
  </color>
  <material>
   Шерсть
  </material>
  <price>
   174319
  </price>
  <rating>
   3.69
  </rating>
  <reviews>
   133504
  </reviews>
  <new>
   -
  </new>
 </clothing>
 <clothing>
  <id>
   212072378
  </id>
  <name>
   New Balance Hat G-3888
  </name>
  <category>
   Hat
  </category>
  <size>
   XL
  </size>
  <color>
   Синий
  </color>
  <material>
   Нейлон
  </material>
  <price>
   837361
  </price>
  <rating>
   2.5
  </rating>
  <reviews>
   119118
  </reviews>
  <new>
   -
  </new>
  <sporty>
   yes
  </sporty>
 </clothing>
 <clothing>
  <id>
   594762998
  </id>
  <name>
   New Balance Handbags A-2841
  </name>
  <category>
   Handbags
  </category>
  <size>
   M
  </size>
  <color>
   Красный
  </color>
  <material>
   Хлопок
  </material>
  <price>
   869096
  </price>
  <rating>
   3.42
  </rating>
  <reviews>
   160164
  </reviews>
  <exclusive>
   no
  </exclusive>
  <sporty>
   no
  </sporty>
 </clothing>
 <clothing>
  <id>
   633372332
  </id>
  <name>
   Fila Gloves Z-6227
  </name>
  <category>
   Gloves
  </category>
  <size>
   S
  </size>
  <color>
   Желтый
  </color>
  <material>
   Вискоза
  </material>
  <price>
   365976
  </price>
  <rating>
   4.49
  </rating>
  <reviews>
   511986
  </reviews>
  <new>
   +
  </new>
  <sporty>
   no
  </sporty>
 </clothing>
 <clothing>
  <id>
   652942202
  </id>
  <name>
   Fila Jacket B-6362
  </name>
  <category>
   Jacket
  </category>
  <size>
   XL
  </size>
  <color>
   Желтый
  </color>
  <material>
   Хлопок
  </material>
  <price>
   276643
  </price>
  <rating>
   3.99
  </rating>
  <reviews>
   991448
  </reviews>
  <new>
   +
  </new>
  <exclusive>
   yes
  </exclusive>
 </clothing>
 <clothing>
  <id>
   857756439
  </id>
  <name>
   Addidas Sweater D-9956
  </name>
  <category>
   Sweater
  </category>
  <size>
   S
  </size>
  <color>
   Красный
  </color>
  <material>
   Хлопок
  </material>
  <price>
   329751
  </price>
  <rating>
   1.75
  </rating>
  <reviews>
   956198
  </reviews>
  <new>
   -
  </new>
  <sporty>
   no
  </sporty>
 </clothing>
 <clothing>
  <id>
   537946063
  </id>
  <name>
   Vans Jacket F-5267
  </name>
  <category>
   Jacket
  </category>
  <size>
   S
  </size>
  <color>
   Фиолетовый
  </color>
  <material>
   Кожа
  </material>
  <price>
   273516
  </price>
  <rating>
   1.44
  </rating>
  <reviews>
   239049
  </reviews>
  <exclusive>
   yes
  </exclusive>
  <sporty>
   no
  </sporty>
 </clothing>
 <clothing>
  <id>
   689226620
  </id>
  <name>
   Reebok Blouse Y-4870
  </name>
  <category>
   Blouse
  </category>
  <size>
   L
  </size>
  <color>
   Синий
  </color>
  <material>
   Шелк
  </material>
  <price>
   406105
  </price>
  <rating>
   3.26
  </rating>
  <reviews>
   570698
  </reviews>
  <exclusive>
   no
  </exclusive>
 </clothing>
 <clothing>
  <id>
   507465332
  </id>
  <name>
   Nike Socks U-1866
  </name>
  <category>
   Socks
  </category>
  <size>
   M
  </size>
  <color>
   Красный
  </color>
  <material>
   Вискоза
  </material>
  <price>
   488095
  </price>
  <rating>
   1.12
  </rating>
  <reviews>
   795271
  </reviews>
  <new>
   -
  </new>
  <exclusive>
   no
  </exclusive>
  <sporty>
   yes
  </sporty>
 </clothing>
 <clothing>
  <id>
   732458276
  </id>
  <name>
   Vans Shoes H-2866
  </name>
  <category>
   Shoes
  </category>
  <size>
   M
  </size>
  <color>
   Синий
  </color>
  <material>
   Вискоза
  </material>
  <price>
   950031
  </price>
  <rating>
   3.52
  </rating>
  <reviews>
   238665
  </reviews>
  <new>
   -
  </new>
  <exclusive>
   no
  </exclusive>
  <sporty>
   no
  </sporty>
 </clothing>
</clothing-items>
