<?xml version="1.0" encoding="utf-8"?>
<clothing-items>
 <clothing>
  <id>
   867804638
  </id>
  <name>
   Under Armour Gloves P-7212
  </name>
  <category>
   Gloves
  </category>
  <size>
   M
  </size>
  <color>
   Синий
  </color>
  <material>
   Лен
  </material>
  <price>
   260458
  </price>
  <rating>
   1.64
  </rating>
  <reviews>
   445409
  </reviews>
  <new>
   -
  </new>
  <exclusive>
   yes
  </exclusive>
  <sporty>
   yes
  </sporty>
 </clothing>
 <clothing>
  <id>
   779522790
  </id>
  <name>
   New Balance Pants R-1219
  </name>
  <category>
   Pants
  </category>
  <size>
   M
  </size>
  <color>
   Синий
  </color>
  <material>
   Нейлон
  </material>
  <price>
   230815
  </price>
  <rating>
   2.38
  </rating>
  <reviews>
   663655
  </reviews>
  <new>
   +
  </new>
 </clothing>
 <clothing>
  <id>
   607281734
  </id>
  <name>
   DC Handbags N-7972
  </name>
  <category>
   Handbags
  </category>
  <size>
   M
  </size>
  <color>
   Красный
  </color>
  <material>
   Кожа
  </material>
  <price>
   111951
  </price>
  <rating>
   2.28
  </rating>
  <reviews>
   373491
  </reviews>
  <new>
   +
  </new>
  <sporty>
   yes
  </sporty>
 </clothing>
 <clothing>
  <id>
   646271038
  </id>
  <name>
   Puma T-shirt V-3192
  </name>
  <category>
   T-shirt
  </category>
  <size>
   L
  </size>
  <color>
   Желтый
  </color>
  <material>
   Нейлон
  </material>
  <price>
   647015
  </price>
  <rating>
   3.44
  </rating>
  <reviews>
   923512
  </reviews>
  <sporty>
   yes
  </sporty>
 </clothing>
 <clothing>
  <id>
   864473920
  </id>
  <name>
   Converse Jeans H-1892
  </name>
  <category>
   Jeans
  </category>
  <size>
   L
  </size>
  <color>
   Голубой
  </color>
  <material>
   Шелк
  </material>
  <price>
   240499
  </price>
  <rating>
   1.55
  </rating>
  <reviews>
   720706
  </reviews>
  <new>
   +
  </new>
  <exclusive>
   yes
  </exclusive>
 </clothing>
 <clothing>
  <id>
   259248862
  </id>
  <name>
   Brooks Belts E-6776
  </name>
  <category>
   Belts
  </category>
  <size>
   S
  </size>
  <color>
   Желтый
  </color>
  <material>
   Вискоза
  </material>
  <price>
   278917
  </price>
  <rating>
   4.98
  </rating>
  <reviews>
   972534
  </reviews>
  <new>
   -
  </new>
  <sporty>
   no
  </sporty>
 </clothing>
 <clothing>
  <id>
   279640965
  </id>
  <name>
   New Balance Gloves Q-2099
  </name>
  <category>
   Gloves
  </category>
  <size>
   XXL
  </size>
  <color>
   Фиолетовый
  </color>
  <material>
   Нейлон
  </material>
  <price>
   449413
  </price>
  <rating>
   2.13
  </rating>
  <reviews>
   869125
  </reviews>
  <exclusive>
   no
  </exclusive>
  <sporty>
   no
  </sporty>
 </clothing>
 <clothing>
  <id>
   356785983
  </id>
  <name>
   Brooks Sweater G-8335
  </name>
  <category>
   Sweater
  </category>
  <size>
   M
  </size>
  <color>
   Фиолетовый
  </color>
  <material>
   Хлопок
  </material>
  <price>
   633609
  </price>
  <rating>
   1.91
  </rating>
  <reviews>
   861891
  </reviews>
  <new>
   +
  </new>
  <exclusive>
   yes
  </exclusive>
 </clothing>
 <clothing>
  <id>
   916971090
  </id>
  <name>
   Adidas Sweater V-4462
  </name>
  <category>
   Sweater
  </category>
  <size>
   L
  </size>
  <color>
   Голубой
  </color>
  <material>
   Шелк
  </material>
  <price>
   465984
  </price>
  <rating>
   3.1
  </rating>
  <reviews>
   388345
  </reviews>
  <new>
   +
  </new>
  <exclusive>
   no
  </exclusive>
  <sporty>
   yes
  </sporty>
 </clothing>
 <clothing>
  <id>
   779106177
  </id>
  <name>
   Vans Shoes C-2786
  </name>
  <category>
   Shoes
  </category>
  <size>
   S
  </size>
  <color>
   Красный
  </color>
  <material>
   Лен
  </material>
  <price>
   488775
  </price>
  <rating>
   1.74
  </rating>
  <reviews>
   494798
  </reviews>
  <new>
   -
  </new>
  <exclusive>
   no
  </exclusive>
 </clothing>
 <clothing>
  <id>
   840627674
  </id>
  <name>
   Asics Dress Z-4884
  </name>
  <category>
   Dress
  </category>
  <size>
   XXL
  </size>
  <color>
   Синий
  </color>
  <material>
   Нейлон
  </material>
  <price>
   694415
  </price>
  <rating>
   3.8
  </rating>
  <reviews>
   694054
  </reviews>
  <exclusive>
   no
  </exclusive>
  <sporty>
   yes
  </sporty>
 </clothing>
 <clothing>
  <id>
   638539308
  </id>
  <name>
   Ellesse Gloves M-5803
  </name>
  <category>
   Gloves
  </category>
  <size>
   XL
  </size>
  <color>
   Желтый
  </color>
  <material>
   Шелк
  </material>
  <price>
   122278
  </price>
  <rating>
   1.49
  </rating>
  <reviews>
   172833
  </reviews>
  <new>
   -
  </new>
  <sporty>
   yes
  </sporty>
 </clothing>
 <clothing>
  <id>
   544808340
  </id>
  <name>
   Addidas T-shirt S-2337
  </name>
  <category>
   T-shirt
  </category>
  <size>
   L
  </size>
  <color>
   Голубой
  </color>
  <material>
   Кожа
  </material>
  <price>
   496442
  </price>
  <rating>
   3.99
  </rating>
  <reviews>
   713087
  </reviews>
  <new>
   +
  </new>
  <sporty>
   no
  </sporty>
 </clothing>
 <clothing>
  <id>
   858306539
  </id>
  <name>
   New Balance Hat G-4977
  </name>
  <category>
   Hat
  </category>
  <size>
   XL
  </size>
  <color>
   Желтый
  </color>
  <material>
   Лен
  </material>
  <price>
   744586
  </price>
  <rating>
   4.68
  </rating>
  <reviews>
   549168
  </reviews>
  <new>
   -
  </new>
 </clothing>
 <clothing>
  <id>
   379751793
  </id>
  <name>
   Lacoste T-shirt R-2234
  </name>
  <category>
   T-shirt
  </category>
  <size>
   M
  </size>
  <color>
   Голубой
  </color>
  <material>
   Вискоза
  </material>
  <price>
   235429
  </price>
  <rating>
   4.5
  </rating>
  <reviews>
   89393
  </reviews>
  <exclusive>
   no
  </exclusive>
 </clothing>
 <clothing>
  <id>
   149456275
  </id>
  <name>
   Brooks Dress T-7452
  </name>
  <category>
   Dress
  </category>
  <size>
   L
  </size>
  <color>
   Зеленый
  </color>
  <material>
   Кожа
  </material>
  <price>
   861014
  </price>
  <rating>
   2.79
  </rating>
  <reviews>
   629799
  </reviews>
  <new>
   -
  </new>
  <sporty>
   no
  </sporty>
 </clothing>
 <clothing>
  <id>
   805089307
  </id>
  <name>
   Addidas Jeans N-6601
  </name>
  <category>
   Jeans
  </category>
  <size>
   XL
  </size>
  <color>
   Фиолетовый
  </color>
  <material>
   Лен
  </material>
  <price>
   184625
  </price>
  <rating>
   4.06
  </rating>
  <reviews>
   952890
  </reviews>
  <new>
   -
  </new>
  <exclusive>
   no
  </exclusive>
 </clothing>
 <clothing>
  <id>
   421624151
  </id>
  <name>
   DC Gloves G-3357
  </name>
  <category>
   Gloves
  </category>
  <size>
   M
  </size>
  <color>
   Голубой
  </color>
  <material>
   Хлопок
  </material>
  <price>
   447160
  </price>
  <rating>
   3.4
  </rating>
  <reviews>
   71248
  </reviews>
  <new>
   +
  </new>
  <sporty>
   yes
  </sporty>
 </clothing>
 <clothing>
  <id>
   185628760
  </id>
  <name>
   Converse Handbags P-6499
  </name>
  <category>
   Handbags
  </category>
  <size>
   S
  </size>
  <color>
   Голубой
  </color>
  <material>
   Шерсть
  </material>
  <price>
   740269
  </price>
  <rating>
   4.23
  </rating>
  <reviews>
   454163
  </reviews>
  <sporty>
   yes
  </sporty>
 </clothing>
 <clothing>
  <id>
   778967139
  </id>
  <name>
   Asics Handbags J-5565
  </name>
  <category>
   Handbags
  </category>
  <size>
   XXL
  </size>
  <color>
   Желтый
  </color>
  <material>
   Шелк
  </material>
  <price>
   504321
  </price>
  <rating>
   4.25
  </rating>
  <reviews>
   953516
  </reviews>
  <new>
   -
  </new>
  <exclusive>
   no
  </exclusive>
  <sporty>
   yes
  </sporty>
 </clothing>
 <clothing>
  <id>
   182266574
  </id>
  <name>
   Puma Blouse K-9314
  </name>
  <category>
   Blouse
  </category>
  <size>
   M
  </size>
  <color>
   Фиолетовый
  </color>
  <material>
   Лен
  </material>
  <price>
   583992
  </price>
  <rating>
   3.09
  </rating>
  <reviews>
   376669
  </reviews>
  <sporty>
   no
  </sporty>
 </clothing>
 <clothing>
  <id>
   600906136
  </id>
  <name>
   PleinSport Skirt B-6645
  </name>
  <category>
   Skirt
  </category>
  <size>
   XXL
  </size>
  <color>
   Фиолетовый
  </color>
  <material>
   Полиэстер
  </material>
  <price>
   824932
  </price>
  <rating>
   1.92
  </rating>
  <reviews>
   42902
  </reviews>
  <new>
   +
  </new>
  <exclusive>
   no
  </exclusive>
  <sporty>
   no
  </sporty>
 </clothing>
 <clothing>
  <id>
   657699936
  </id>
  <name>
   Addidas Blouse B-2938
  </name>
  <category>
   Blouse
  </category>
  <size>
   XL
  </size>
  <color>
   Оранжевый
  </color>
  <material>
   Шерсть
  </material>
  <price>
   567935
  </price>
  <rating>
   1.09
  </rating>
  <reviews>
   999404
  </reviews>
  <new>
   -
  </new>
  <exclusive>
   no
  </exclusive>
 </clothing>
 <clothing>
  <id>
   211561517
  </id>
  <name>
   Addidas Sweater Q-6589
  </name>
  <category>
   Sweater
  </category>
  <size>
   M
  </size>
  <color>
   Зеленый
  </color>
  <material>
   Вискоза
  </material>
  <price>
   106953
  </price>
  <rating>
   4.24
  </rating>
  <reviews>
   981437
  </reviews>
 </clothing>
 <clothing>
  <id>
   851449361
  </id>
  <name>
   Lacoste Belts H-4595
  </name>
  <category>
   Belts
  </category>
  <size>
   XL
  </size>
  <color>
   Голубой
  </color>
  <material>
   Лен
  </material>
  <price>
   783262
  </price>
  <rating>
   4.65
  </rating>
  <reviews>
   453961
  </reviews>
  <new>
   +
  </new>
  <exclusive>
   yes
  </exclusive>
  <sporty>
   no
  </sporty>
 </clothing>
 <clothing>
  <id>
   933804423
  </id>
  <name>
   Asics Gloves J-8505
  </name>
  <category>
   Gloves
  </category>
  <size>
   XXL
  </size>
  <color>
   Желтый
  </color>
  <material>
   Лен
  </material>
  <price>
   828826
  </price>
  <rating>
   1.23
  </rating>
  <reviews>
   749664
  </reviews>
  <new>
   -
  </new>
  <sporty>
   no
  </sporty>
 </clothing>
 <clothing>
  <id>
   675477881
  </id>
  <name>
   Brooks Handbags E-9903
  </name>
  <category>
   Handbags
  </category>
  <size>
   M
  </size>
  <color>
   Оранжевый
  </color>
  <material>
   Хлопок
  </material>
  <price>
   124679
  </price>
  <rating>
   1.91
  </rating>
  <reviews>
   73101
  </reviews>
  <new>
   -
  </new>
  <exclusive>
   yes
  </exclusive>
 </clothing>
 <clothing>
  <id>
   702053155
  </id>
  <name>
   Under Armour Umbrellas B-3710
  </name>
  <category>
   Umbrellas
  </category>
  <size>
   S
  </size>
  <color>
   Фиолетовый
  </color>
  <material>
   Кожа
  </material>
  <price>
   681092
  </price>
  <rating>
   2.38
  </rating>
  <reviews>
   559591
  </reviews>
  <sporty>
   no
  </sporty>
 </clothing>
 <clothing>
  <id>
   140805686
  </id>
  <name>
   Addidas Skirt J-8154
  </name>
  <category>
   Skirt
  </category>
  <size>
   L
  </size>
  <color>
   Зеленый
  </color>
  <material>
   Шерсть
  </material>
  <price>
   591590
  </price>
  <rating>
   3.59
  </rating>
  <reviews>
   197148
  </reviews>
  <new>
   -
  </new>
  <exclusive>
   yes
  </exclusive>
  <sporty>
   no
  </sporty>
 </clothing>
 <clothing>
  <id>
   148518011
  </id>
  <name>
   Asics Hat R-8745
  </name>
  <category>
   Hat
  </category>
  <size>
   L
  </size>
  <color>
   Голубой
  </color>
  <material>
   Лен
  </material>
  <price>
   504148
  </price>
  <rating>
   4.01
  </rating>
  <reviews>
   447243
  </reviews>
  <new>
   +
  </new>
  <exclusive>
   yes
  </exclusive>
  <sporty>
   yes
  </sporty>
 </clothing>
 <clothing>
  <id>
   571790207
  </id>
  <name>
   Brooks Skirt P-9610
  </name>
  <category>
   Skirt
  </category>
  <size>
   XXL
  </size>
  <color>
   Фиолетовый
  </color>
  <material>
   Нейлон
  </material>
  <price>
   569043
  </price>
  <rating>
   2.34
  </rating>
  <reviews>
   132682
  </reviews>
  <new>
   +
  </new>
  <exclusive>
   no
  </exclusive>
  <sporty>
   yes
  </sporty>
 </clothing>
 <clothing>
  <id>
   228700700
  </id>
  <name>
   Lacoste Umbrellas V-1639
  </name>
  <category>
   Umbrellas
  </category>
  <size>
   L
  </size>
  <color>
   Синий
  </color>
  <material>
   Шерсть
  </material>
  <price>
   984651
  </price>
  <rating>
   1.84
  </rating>
  <reviews>
   656967
  </reviews>
  <new>
   -
  </new>
  <exclusive>
   no
  </exclusive>
  <sporty>
   no
  </sporty>
 </clothing>
 <clothing>
  <id>
   168458156
  </id>
  <name>
   Adidas Sweater B-3025
  </name>
  <category>
   Sweater
  </category>
  <size>
   L
  </size>
  <color>
   Красный
  </color>
  <material>
   Кожа
  </material>
  <price>
   343816
  </price>
  <rating>
   4.75
  </rating>
  <reviews>
   595312
  </reviews>
  <new>
   -
  </new>
  <exclusive>
   yes
  </exclusive>
  <sporty>
   no
  </sporty>
 </clothing>
 <clothing>
  <id>
   992377578
  </id>
  <name>
   Nike Blouse U-2165
  </name>
  <category>
   Blouse
  </category>
  <size>
   L
  </size>
  <color>
   Голубой
  </color>
  <material>
   Шерсть
  </material>
  <price>
   601913
  </price>
  <rating>
   3.41
  </rating>
  <reviews>
   259456
  </reviews>
  <new>
   -
  </new>
  <exclusive>
   yes
  </exclusive>
  <sporty>
   no
  </sporty>
 </clothing>
 <clothing>
  <id>
   990388152
  </id>
  <name>
   DC T-shirt W-8521
  </name>
  <category>
   T-shirt
  </category>
  <size>
   M
  </size>
  <color>
   Синий
  </color>
  <material>
   Шерсть
  </material>
  <price>
   618702
  </price>
  <rating>
   1.8
  </rating>
  <reviews>
   938553
  </reviews>
  <exclusive>
   no
  </exclusive>
  <sporty>
   no
  </sporty>
 </clothing>
 <clothing>
  <id>
   182148688
  </id>
  <name>
   Lacoste Umbrellas L-4397
  </name>
  <category>
   Umbrellas
  </category>
  <size>
   S
  </size>
  <color>
   Голубой
  </color>
  <material>
   Кожа
  </material>
  <price>
   224194
  </price>
  <rating>
   1.22
  </rating>
  <reviews>
   561932
  </reviews>
  <new>
   +
  </new>
  <exclusive>
   yes
  </exclusive>
 </clothing>
 <clothing>
  <id>
   926690941
  </id>
  <name>
   Vans Dress W-6807
  </name>
  <category>
   Dress
  </category>
  <size>
   L
  </size>
  <color>
   Красный
  </color>
  <material>
   Лен
  </material>
  <price>
   774420
  </price>
  <rating>
   3.92
  </rating>
  <reviews>
   209674
  </reviews>
 </clothing>
 <clothing>
  <id>
   785896643
  </id>
  <name>
   Under Armour Blouse P-9348
  </name>
  <category>
   Blouse
  </category>
  <size>
   XL
  </size>
  <color>
   Оранжевый
  </color>
  <material>
   Лен
  </material>
  <price>
   611759
  </price>
  <rating>
   2.96
  </rating>
  <reviews>
   112364
  </reviews>
  <sporty>
   yes
  </sporty>
 </clothing>
</clothing-items>
