<?xml version="1.0" encoding="utf-8"?>
<clothing-items>
 <clothing>
  <id>
   190461652
  </id>
  <name>
   Converse T-shirt I-2760
  </name>
  <category>
   T-shirt
  </category>
  <size>
   XL
  </size>
  <color>
   Фиолетовый
  </color>
  <material>
   Кожа
  </material>
  <price>
   165808
  </price>
  <rating>
   4.21
  </rating>
  <reviews>
   614594
  </reviews>
  <new>
   -
  </new>
 </clothing>
 <clothing>
  <id>
   715597686
  </id>
  <name>
   Puma Umbrellas V-6228
  </name>
  <category>
   Umbrellas
  </category>
  <size>
   S
  </size>
  <color>
   Зеленый
  </color>
  <material>
   Нейлон
  </material>
  <price>
   795701
  </price>
  <rating>
   3.18
  </rating>
  <reviews>
   813940
  </reviews>
 </clothing>
 <clothing>
  <id>
   571701564
  </id>
  <name>
   Vans Socks K-6715
  </name>
  <category>
   Socks
  </category>
  <size>
   XXL
  </size>
  <color>
   Фиолетовый
  </color>
  <material>
   Шерсть
  </material>
  <price>
   434598
  </price>
  <rating>
   1.55
  </rating>
  <reviews>
   61389
  </reviews>
  <exclusive>
   yes
  </exclusive>
  <sporty>
   no
  </sporty>
 </clothing>
 <clothing>
  <id>
   903409156
  </id>
  <name>
   Converse Umbrellas K-9429
  </name>
  <category>
   Umbrellas
  </category>
  <size>
   XL
  </size>
  <color>
   Голубой
  </color>
  <material>
   Нейлон
  </material>
  <price>
   533017
  </price>
  <rating>
   3.54
  </rating>
  <reviews>
   976530
  </reviews>
  <new>
   -
  </new>
  <sporty>
   yes
  </sporty>
 </clothing>
 <clothing>
  <id>
   180664419
  </id>
  <name>
   Adidas Shoes I-7047
  </name>
  <category>
   Shoes
  </category>
  <size>
   L
  </size>
  <color>
   Зеленый
  </color>
  <material>
   Полиэстер
  </material>
  <price>
   591791
  </price>
  <rating>
   4.62
  </rating>
  <reviews>
   657992
  </reviews>
  <exclusive>
   no
  </exclusive>
 </clothing>
 <clothing>
  <id>
   848869959
  </id>
  <name>
   Under Armour Shirt T-4392
  </name>
  <category>
   Shirt
  </category>
  <size>
   S
  </size>
  <color>
   Оранжевый
  </color>
  <material>
   Кожа
  </material>
  <price>
   947943
  </price>
  <rating>
   1.48
  </rating>
  <reviews>
   961418
  </reviews>
  <new>
   +
  </new>
  <sporty>
   no
  </sporty>
 </clothing>
 <clothing>
  <id>
   400881147
  </id>
  <name>
   Addidas T-shirt D-2117
  </name>
  <category>
   T-shirt
  </category>
  <size>
   L
  </size>
  <color>
   Синий
  </color>
  <material>
   Шелк
  </material>
  <price>
   963333
  </price>
  <rating>
   2.35
  </rating>
  <reviews>
   206613
  </reviews>
  <exclusive>
   yes
  </exclusive>
  <sporty>
   no
  </sporty>
 </clothing>
 <clothing>
  <id>
   529796969
  </id>
  <name>
   Ellesse Handbags W-4205
  </name>
  <category>
   Handbags
  </category>
  <size>
   S
  </size>
  <color>
   Фиолетовый
  </color>
  <material>
   Вискоза
  </material>
  <price>
   375765
  </price>
  <rating>
   4.49
  </rating>
  <reviews>
   685324
  </reviews>
 </clothing>
 <clothing>
  <id>
   499193791
  </id>
  <name>
   Converse Socks Z-2694
  </name>
  <category>
   Socks
  </category>
  <size>
   XXL
  </size>
  <color>
   Фиолетовый
  </color>
  <material>
   Хлопок
  </material>
  <price>
   219875
  </price>
  <rating>
   1.12
  </rating>
  <reviews>
   790675
  </reviews>
  <exclusive>
   no
  </exclusive>
  <sporty>
   no
  </sporty>
 </clothing>
 <clothing>
  <id>
   614621604
  </id>
  <name>
   Nike Jacket U-4474
  </name>
  <category>
   Jacket
  </category>
  <size>
   L
  </size>
  <color>
   Фиолетовый
  </color>
  <material>
   Вискоза
  </material>
  <price>
   368302
  </price>
  <rating>
   2.27
  </rating>
  <reviews>
   503219
  </reviews>
  <new>
   -
  </new>
  <exclusive>
   no
  </exclusive>
 </clothing>
 <clothing>
  <id>
   935129693
  </id>
  <name>
   Lacoste Handbags U-2835
  </name>
  <category>
   Handbags
  </category>
  <size>
   S
  </size>
  <color>
   Желтый
  </color>
  <material>
   Нейлон
  </material>
  <price>
   201106
  </price>
  <rating>
   3.26
  </rating>
  <reviews>
   346383
  </reviews>
  <exclusive>
   no
  </exclusive>
  <sporty>
   no
  </sporty>
 </clothing>
 <clothing>
  <id>
   151004442
  </id>
  <name>
   Nike Pants K-1870
  </name>
  <category>
   Pants
  </category>
  <size>
   XL
  </size>
  <color>
   Оранжевый
  </color>
  <material>
   Хлопок
  </material>
  <price>
   437121
  </price>
  <rating>
   2.24
  </rating>
  <reviews>
   409846
  </reviews>
  <new>
   +
  </new>
  <exclusive>
   no
  </exclusive>
  <sporty>
   yes
  </sporty>
 </clothing>
 <clothing>
  <id>
   549898446
  </id>
  <name>
   New Balance Hat E-4123
  </name>
  <category>
   Hat
  </category>
  <size>
   L
  </size>
  <color>
   Фиолетовый
  </color>
  <material>
   Шелк
  </material>
  <price>
   801765
  </price>
  <rating>
   4.33
  </rating>
  <reviews>
   450862
  </reviews>
  <new>
   -
  </new>
  <sporty>
   yes
  </sporty>
 </clothing>
 <clothing>
  <id>
   625568994
  </id>
  <name>
   Lacoste Belts O-6355
  </name>
  <category>
   Belts
  </category>
  <size>
   S
  </size>
  <color>
   Фиолетовый
  </color>
  <material>
   Нейлон
  </material>
  <price>
   823638
  </price>
  <rating>
   2.87
  </rating>
  <reviews>
   42549
  </reviews>
  <new>
   +
  </new>
  <exclusive>
   yes
  </exclusive>
  <sporty>
   no
  </sporty>
 </clothing>
 <clothing>
  <id>
   938765420
  </id>
  <name>
   Lacoste Socks G-3992
  </name>
  <category>
   Socks
  </category>
  <size>
   XXL
  </size>
  <color>
   Фиолетовый
  </color>
  <material>
   Хлопок
  </material>
  <price>
   672683
  </price>
  <rating>
   2.08
  </rating>
  <reviews>
   830123
  </reviews>
 </clothing>
 <clothing>
  <id>
   648184041
  </id>
  <name>
   Lacoste Umbrellas Q-1325
  </name>
  <category>
   Umbrellas
  </category>
  <size>
   S
  </size>
  <color>
   Желтый
  </color>
  <material>
   Полиэстер
  </material>
  <price>
   759076
  </price>
  <rating>
   1.25
  </rating>
  <reviews>
   985261
  </reviews>
  <sporty>
   no
  </sporty>
 </clothing>
 <clothing>
  <id>
   669067603
  </id>
  <name>
   Addidas Belts K-4497
  </name>
  <category>
   Belts
  </category>
  <size>
   XXL
  </size>
  <color>
   Красный
  </color>
  <material>
   Кожа
  </material>
  <price>
   520524
  </price>
  <rating>
   3.91
  </rating>
  <reviews>
   742752
  </reviews>
  <new>
   +
  </new>
  <sporty>
   no
  </sporty>
 </clothing>
 <clothing>
  <id>
   240331214
  </id>
  <name>
   Nike Socks C-7515
  </name>
  <category>
   Socks
  </category>
  <size>
   L
  </size>
  <color>
   Зеленый
  </color>
  <material>
   Шерсть
  </material>
  <price>
   586188
  </price>
  <rating>
   2.6
  </rating>
  <reviews>
   294761
  </reviews>
  <sporty>
   yes
  </sporty>
 </clothing>
 <clothing>
  <id>
   132148054
  </id>
  <name>
   New Balance Belts V-5303
  </name>
  <category>
   Belts
  </category>
  <size>
   XXL
  </size>
  <color>
   Оранжевый
  </color>
  <material>
   Полиэстер
  </material>
  <price>
   445966
  </price>
  <rating>
   1.11
  </rating>
  <reviews>
   874331
  </reviews>
  <exclusive>
   no
  </exclusive>
  <sporty>
   no
  </sporty>
 </clothing>
 <clothing>
  <id>
   683510211
  </id>
  <name>
   Reebok Handbags O-3598
  </name>
  <category>
   Handbags
  </category>
  <size>
   S
  </size>
  <color>
   Синий
  </color>
  <material>
   Кожа
  </material>
  <price>
   470442
  </price>
  <rating>
   2.03
  </rating>
  <reviews>
   460055
  </reviews>
  <new>
   -
  </new>
  <sporty>
   no
  </sporty>
 </clothing>
 <clothing>
  <id>
   753649092
  </id>
  <name>
   PleinSport Socks T-6951
  </name>
  <category>
   Socks
  </category>
  <size>
   XL
  </size>
  <color>
   Зеленый
  </color>
  <material>
   Шелк
  </material>
  <price>
   164714
  </price>
  <rating>
   4.22
  </rating>
  <reviews>
   207706
  </reviews>
  <exclusive>
   yes
  </exclusive>
  <sporty>
   yes
  </sporty>
 </clothing>
 <clothing>
  <id>
   357027364
  </id>
  <name>
   Vans Jeans V-9247
  </name>
  <category>
   Jeans
  </category>
  <size>
   XL
  </size>
  <color>
   Синий
  </color>
  <material>
   Шелк
  </material>
  <price>
   126314
  </price>
  <rating>
   3.42
  </rating>
  <reviews>
   207376
  </reviews>
  <new>
   +
  </new>
  <exclusive>
   yes
  </exclusive>
 </clothing>
 <clothing>
  <id>
   909883070
  </id>
  <name>
   Asics Hat H-9869
  </name>
  <category>
   Hat
  </category>
  <size>
   M
  </size>
  <color>
   Красный
  </color>
  <material>
   Шерсть
  </material>
  <price>
   105020
  </price>
  <rating>
   4.3
  </rating>
  <reviews>
   521925
  </reviews>
  <new>
   +
  </new>
  <exclusive>
   no
  </exclusive>
  <sporty>
   yes
  </sporty>
 </clothing>
 <clothing>
  <id>
   110369976
  </id>
  <name>
   Puma Handbags Q-8137
  </name>
  <category>
   Handbags
  </category>
  <size>
   XL
  </size>
  <color>
   Фиолетовый
  </color>
  <material>
   Шелк
  </material>
  <price>
   423167
  </price>
  <rating>
   4.57
  </rating>
  <reviews>
   176869
  </reviews>
  <new>
   +
  </new>
  <sporty>
   no
  </sporty>
 </clothing>
 <clothing>
  <id>
   714176642
  </id>
  <name>
   Lacoste Jacket P-3881
  </name>
  <category>
   Jacket
  </category>
  <size>
   XXL
  </size>
  <color>
   Голубой
  </color>
  <material>
   Полиэстер
  </material>
  <price>
   449091
  </price>
  <rating>
   1.73
  </rating>
  <reviews>
   907083
  </reviews>
  <new>
   -
  </new>
  <exclusive>
   yes
  </exclusive>
 </clothing>
 <clothing>
  <id>
   686908446
  </id>
  <name>
   Adidas Sweater C-4173
  </name>
  <category>
   Sweater
  </category>
  <size>
   XXL
  </size>
  <color>
   Красный
  </color>
  <material>
   Вискоза
  </material>
  <price>
   967663
  </price>
  <rating>
   4.35
  </rating>
  <reviews>
   328516
  </reviews>
  <exclusive>
   yes
  </exclusive>
 </clothing>
 <clothing>
  <id>
   957897313
  </id>
  <name>
   Ellesse Belts C-8714
  </name>
  <category>
   Belts
  </category>
  <size>
   L
  </size>
  <color>
   Желтый
  </color>
  <material>
   Вискоза
  </material>
  <price>
   431029
  </price>
  <rating>
   3.63
  </rating>
  <reviews>
   845283
  </reviews>
  <new>
   +
  </new>
  <exclusive>
   yes
  </exclusive>
 </clothing>
 <clothing>
  <id>
   352734092
  </id>
  <name>
   Under Armour Jeans D-8361
  </name>
  <category>
   Jeans
  </category>
  <size>
   XL
  </size>
  <color>
   Красный
  </color>
  <material>
   Нейлон
  </material>
  <price>
   532406
  </price>
  <rating>
   3.79
  </rating>
  <reviews>
   983369
  </reviews>
  <exclusive>
   no
  </exclusive>
 </clothing>
 <clothing>
  <id>
   560172263
  </id>
  <name>
   Ellesse T-shirt Z-6098
  </name>
  <category>
   T-shirt
  </category>
  <size>
   XXL
  </size>
  <color>
   Красный
  </color>
  <material>
   Хлопок
  </material>
  <price>
   195923
  </price>
  <rating>
   2.95
  </rating>
  <reviews>
   139448
  </reviews>
  <exclusive>
   no
  </exclusive>
 </clothing>
 <clothing>
  <id>
   769531067
  </id>
  <name>
   Asics Jacket T-8046
  </name>
  <category>
   Jacket
  </category>
  <size>
   XL
  </size>
  <color>
   Синий
  </color>
  <material>
   Шерсть
  </material>
  <price>
   741172
  </price>
  <rating>
   2.84
  </rating>
  <reviews>
   79053
  </reviews>
  <new>
   -
  </new>
  <sporty>
   yes
  </sporty>
 </clothing>
 <clothing>
  <id>
   371489092
  </id>
  <name>
   Vans T-shirt U-2241
  </name>
  <category>
   T-shirt
  </category>
  <size>
   S
  </size>
  <color>
   Красный
  </color>
  <material>
   Нейлон
  </material>
  <price>
   420277
  </price>
  <rating>
   2.94
  </rating>
  <reviews>
   811992
  </reviews>
  <exclusive>
   no
  </exclusive>
  <sporty>
   yes
  </sporty>
 </clothing>
</clothing-items>
